odoo/addons/l10n_it_delivery_note_order_link/README.rst
odoo/addons/l10n_it_delivery_note_order_link/__init__.py
odoo/addons/l10n_it_delivery_note_order_link/__manifest__.py
odoo/addons/l10n_it_delivery_note_order_link/i18n/it.po
odoo/addons/l10n_it_delivery_note_order_link/i18n/l10n_it_delivery_note_order_link.pot
odoo/addons/l10n_it_delivery_note_order_link/models/__init__.py
odoo/addons/l10n_it_delivery_note_order_link/models/purchase_order.py
odoo/addons/l10n_it_delivery_note_order_link/models/sale_order.py
odoo/addons/l10n_it_delivery_note_order_link/models/stock_delivery_note.py
odoo/addons/l10n_it_delivery_note_order_link/readme/CONFIGURE.md
odoo/addons/l10n_it_delivery_note_order_link/readme/CONTRIBUTORS.md
odoo/addons/l10n_it_delivery_note_order_link/readme/DESCRIPTION.md
odoo/addons/l10n_it_delivery_note_order_link/readme/USAGE.md
odoo/addons/l10n_it_delivery_note_order_link/static/description/icon.png
odoo/addons/l10n_it_delivery_note_order_link/static/description/index.html
odoo/addons/l10n_it_delivery_note_order_link/views/purchase_order.xml
odoo/addons/l10n_it_delivery_note_order_link/views/sale_order.xml
odoo_addon_l10n_it_delivery_note_order_link-18.0.1.0.0.2.dist-info/METADATA
odoo_addon_l10n_it_delivery_note_order_link-18.0.1.0.0.2.dist-info/WHEEL
odoo_addon_l10n_it_delivery_note_order_link-18.0.1.0.0.2.dist-info/top_level.txt
odoo_addon_l10n_it_delivery_note_order_link-18.0.1.0.0.2.dist-info/RECORD
